{
      "videoDetails": {
            "VideoLink": "https://www.youtube.com/watch?v=UnfN13_xGQw",
            "ChannelLink": "https://www.youtube.com/channel/UCe1v4VTDtXN_fKYEOAazhYg",
            "VideoId": "UnfN13_xGQw",
            "ChannelId": "UCe1v4VTDtXN_fKYEOAazhYg",
            "Title": "Arcade vs Realistic Tank Battle Differences Explained  War Thunder",
            "ChannelName": "Tankenstein",
            "Description": "I go over every single difference between arcade and realistic in the most comprehensive video of its kind anywhere on Youtube. Let me know if I left anything out!\n\n\nTo support my channel, feel free to subscribe. Thank you!"
      },
      "stats": {
            "ViewCount": 22303,
            "LikeCount": 573,
            "CommentCount": 83,
            "Like2ViewRatio": 0.025691610994036676,
            "Comment2ViewRatio": 0.003721472447652782,
            "Tags": [
                  "\u0432\u0430\u0440 \u0442\u0430\u043d\u0434\u0435\u0440"
            ]
      }
}