{
      "videoDetails": {
            "VideoLink": "https://www.youtube.com/watch?v=v3Dd0BjxI6U",
            "ChannelLink": "https://www.youtube.com/channel/UC-oz7T5VDhkNZTTMSdzZrcQ",
            "VideoId": "v3Dd0BjxI6U",
            "ChannelId": "UC-oz7T5VDhkNZTTMSdzZrcQ",
            "Title": "I Love F-16 Block 10 || Maverick Missile CAS in Ground RB (War Thunder)",
            "ChannelName": "Hunter",
            "Description": "I Hope You Enjoy\n\nMy Patreon:\nhttps://www.patreon.com/hunter_i86\n\nMy PayPal:\nhttps://paypal.me/HunteRi86?locale.x=en_US\n\nMy profile in Gaijin.net//issues https://community.gaijin.net/issues/u/3173968/issues\n\nMy Social Media info:\nDiscord https://discord.gg/pqXSHte\n\nMy PC Specs:\nAsus ROG Strix RTX 3080\nIntel Core i7 10700\nDDR4 32GB RAM\nASUS Tuf 27 inch 1440p 144hz Monitor\n\nThank you so much for your precious friendship, it means everything."
      },
      "stats": {
            "ViewCount": "9946",
            "LikeCount": "465",
            "CommentCount": 97,
            "Like2ViewRatio": 0.04675246330182988,
            "Comment2ViewRatio": 0.009752664387693545,
            "Tags": [
                  [
                        "War Thunder",
                        "tanks",
                        "aircrafts",
                        "jet",
                        "CAS",
                        "Close Air Support",
                        "Ground Pounding",
                        "Missile",
                        "RB",
                        "SAM",
                        "Helicopter",
                        "Chopper",
                        "Flares",
                        "Tanks RB",
                        "Ground RB",
                        "Sim",
                        "USA",
                        "America",
                        "Russia",
                        "Soviet",
                        "Germany",
                        "British",
                        "UK",
                        "phlydaily",
                        "Bullpup",
                        "epic",
                        "planes",
                        "Ka-50",
                        "Gameplay",
                        "Carpet Bombing",
                        "Rolling Thunder",
                        "Dive Bombing",
                        "Warthog",
                        "Mirage F1",
                        "APS",
                        "F-14 Tomcat",
                        "TV",
                        "Laser",
                        "Thermal",
                        "Radar",
                        "Drone Age",
                        "Mirage 2000",
                        "Su-25",
                        "Harrier GR.7",
                        "Z-10",
                        "A-10 Warthog",
                        "F-16",
                        "MiG-29",
                        "4th Gen",
                        "Tornado",
                        "Pantsir-S1"
                  ]
            ]
      }
}